marude/CloudVoiceClient.py
marude/__init__.py
marude/__main__.py
marude-0.3.0.dist-info/LICENSE
marude-0.3.0.dist-info/METADATA
marude-0.3.0.dist-info/WHEEL
marude-0.3.0.dist-info/top_level.txt
marude-0.3.0.dist-info/RECORD
