Metadata-Version: 2.1
Name: marude
Version: 0.3.0
Summary: An http api client which allows to automatically convert russian short texts into speech using vk cloud
Home-page: https://github.com/zeionara/marude
Author: Zeio Nara
Classifier: Programming Language :: Python :: 3.10
License-File: LICENSE
Requires-Dist: click
Requires-Dist: tastier
Requires-Dist: requests
